paper_tabular_dl_revisiting_models.py
paper_tabular_dl_revisiting_models-0.0.5.dist-info/LICENSE
paper_tabular_dl_revisiting_models-0.0.5.dist-info/WHEEL
paper_tabular_dl_revisiting_models-0.0.5.dist-info/METADATA
paper_tabular_dl_revisiting_models-0.0.5.dist-info/RECORD
