Metadata-Version: 2.1
Name: paper_tabular_dl_revisiting_models
Version: 0.0.5
Summary: The official package & illustrations for the NeurIPS 2021 paper "Revisiting Deep Learning Models for Tabular Data".
Keywords: artificial intelligence,deep learning,library,python,pytorch,torch,tabular,tabular data
Author: Yury Gorishniy
Requires-Python: >=3.8
Classifier: Intended Audience :: Developers
Classifier: Intended Audience :: Science/Research
Classifier: License :: OSI Approved :: MIT License
Classifier: Operating System :: MacOS
Classifier: Operating System :: Unix
Classifier: Programming Language :: Python :: 3
Classifier: Topic :: Scientific/Engineering :: Artificial Intelligence
Classifier: Topic :: Software Development :: Libraries :: Python Modules
Requires-Dist: torch >=1.8,<3
Project-URL: Code, https://github.com/yandex-research/tabular-dl-revisiting-models/tree/main/package
Project-URL: Documentation, https://yandex-research.github.io/tabular-dl-revisiting-models
